[{"age":"1.1","code":23040,"gc":"Lo","kd":"name of a concubine of Di Ku, father of the mythical Yao","kc":"sōng","kjo":"shuu shu","name":"CJK UNIFIED IDEOGRAPH-5A00","type":"char"},{"age":"1.1","code":23041,"gc":"Lo","kd":"pomp, power; powerful; dominate","kc":"wēi","kjo":"i","kjk":"odosu takeshi","kk":"wi","kv":"uy","name":"CJK UNIFIED IDEOGRAPH-5A01","type":"char"},{"age":"1.1","code":23042,"gc":"Lo","kc":"hóng","name":"CJK UNIFIED IDEOGRAPH-5A02","type":"char"},{"age":"1.1","code":23043,"gc":"Lo","kd":"baby; doll; pretty girl","kc":"wá wa wā guì","kjo":"a ai","kjk":"utsukushii","kk":"way","name":"CJK UNIFIED IDEOGRAPH-5A03","type":"char"},{"age":"1.1","code":23044,"gc":"Lo","kd":"surname; a constellation; to wear","kc":"lóu lǚ lǘ léi","kjo":"ru rou","kjk":"tsunagu hiku","ky":[23105],"name":"CJK UNIFIED IDEOGRAPH-5A04","type":"char"},{"age":"1.1","code":23045,"gc":"Lo","kd":"mutual term of address used by sons-in-law; a brother-in-law","kc":"yà yā yǎ","ky":[23149],"name":"CJK UNIFIED IDEOGRAPH-5A05","type":"char"},{"age":"1.1","code":23046,"gc":"Lo","kd":"graceful, charming, fascinating","kc":"ráo rǎo yǎo","ky":[23304],"name":"CJK UNIFIED IDEOGRAPH-5A06","type":"char"},{"age":"1.1","code":23047,"gc":"Lo","kd":"seductive and loveable; tender","kc":"jiāo","ky":[23308],"name":"CJK UNIFIED IDEOGRAPH-5A07","type":"char"},{"age":"1.1","code":23048,"gc":"Lo","kd":"lovely, beautiful; docile, obedie","kc":"luán liàn luǎn","ky":[23372],"name":"CJK UNIFIED IDEOGRAPH-5A08","type":"char"},{"age":"1.1","code":23049,"gc":"Lo","kd":"beautiful, attractive, charming, graceful","kc":"pìn pīng","kjo":"hei hou","kjk":"tou","kk":"ping","name":"CJK UNIFIED IDEOGRAPH-5A09","type":"char"},{"age":"1.1","code":23050,"gc":"Lo","kc":"xiàn dān","kjo":"ken gen","name":"CJK UNIFIED IDEOGRAPH-5A0A","type":"char"},{"age":"1.1","code":23051,"gc":"Lo","kc":"shào shāo","name":"CJK UNIFIED IDEOGRAPH-5A0B","type":"char"},{"age":"1.1","code":23052,"gc":"Lo","kd":"brother's wife","kc":"lǐ","kjo":"ri","kjk":"aiyome","name":"CJK UNIFIED IDEOGRAPH-5A0C","type":"char"},{"age":"1.1","code":23053,"gc":"Lo","kc":"chéng shèng","kjo":"sei jou","kjk":"suraritoshitemimeyoi","name":"CJK UNIFIED IDEOGRAPH-5A0D","type":"char"},{"age":"1.1","code":23054,"gc":"Lo","kc":"xiè","kjo":"ketsu kechi kyou","kjk":"kokochiyoi yorokobu","name":"CJK UNIFIED IDEOGRAPH-5A0E","type":"char"},{"age":"1.1","code":23055,"gc":"Lo","kc":"máng","kjo":"bou mou","name":"CJK UNIFIED IDEOGRAPH-5A0F","type":"char"},{"age":"1.1","code":23056,"gc":"Lo","kc":"fū","name":"CJK UNIFIED IDEOGRAPH-5A10","type":"char"},{"age":"1.1","code":23057,"gc":"Lo","kd":"dance, frolic; lounge; saunter","kc":"suō suǒ suò","kjo":"sha sa","kjk":"mau","kk":"sa","name":"CJK UNIFIED IDEOGRAPH-5A11","type":"char"},{"age":"1.1","code":23058,"gc":"Lo","kd":"matron","kc":"mǔ wǔ méi","kjo":"bo mo","kjk":"uba","name":"CJK UNIFIED IDEOGRAPH-5A12","type":"char"},{"age":"1.1","code":23059,"gc":"Lo","kd":"comply; complying, agreeable","kc":"wěi","kjo":"bi mi ki","kjk":"sunao shitagau utsukushii","kk":"mi","kv":"vãi","name":"CJK UNIFIED IDEOGRAPH-5A13","type":"char"},{"age":"1.1","code":23060,"gc":"Lo","kc":"kè","name":"CJK UNIFIED IDEOGRAPH-5A14","type":"char"},{"age":"1.1","code":23061,"gc":"Lo","kc":"chuò cù lài","kjo":"saku shoku soku rai","kjk":"tsutsushimu yoi totonoeru","name":"CJK UNIFIED IDEOGRAPH-5A15","type":"char"},{"age":"1.1","code":23062,"gc":"Lo","kc":"chuò cù","kjo":"saku shoku soku","kjk":"tsutsumu yoi osaeru unagasu","name":"CJK UNIFIED IDEOGRAPH-5A16","type":"char"},{"age":"1.1","code":23063,"gc":"Lo","kc":"tǐng tiǎn","kjo":"tei jou ten","kjk":"suraritoshitemimeyoi","name":"CJK UNIFIED IDEOGRAPH-5A17","type":"char"},{"age":"1.1","code":23064,"gc":"Lo","kd":"mother; young girl; woman; wife","kc":"niang niáng ráng","kjo":"jou nyou","kjk":"musume","kk":"nang","kv":"nương","ky":[23330,23363],"name":"CJK UNIFIED IDEOGRAPH-5A18","type":"char"},{"age":"1.1","code":23065,"gc":"Lo","kc":"xíng","kjo":"gou gyou kou kei","kjk":"suraritoshitemimeyoi hashitaame","kk":"hyeng","name":"CJK UNIFIED IDEOGRAPH-5A19","type":"char"},{"age":"1.1","code":23066,"gc":"Lo","kc":"nán nǎn nǎo nàn","kjo":"nan nou","kjk":"meoto","ky":[21891],"name":"CJK UNIFIED IDEOGRAPH-5A1A","type":"char"},{"age":"1.1","code":23067,"gc":"Lo","kd":"pleasure, enjoyment, amusement","kc":"yú","kjo":"go ku","kjk":"tanoshimu","kk":"o","ky":[23087,23089],"name":"CJK UNIFIED IDEOGRAPH-5A1B","type":"char"},{"age":"1.1","code":23068,"gc":"Lo","kd":"elegant, graceful, delicate","kc":"nuó nà","kjo":"da na","kjk":"shinayaka omomuro","kk":"na","kv":"na","name":"CJK UNIFIED IDEOGRAPH-5A1C","type":"char"},{"age":"1.1","code":23069,"gc":"Lo","kc":"pōu bǐ","name":"CJK UNIFIED IDEOGRAPH-5A1D","type":"char"},{"age":"1.1","code":23070,"gc":"Lo","kc":"něi suī","kjo":"dai ne sui","kjk":"adeyaka yasuraka","name":"CJK UNIFIED IDEOGRAPH-5A1E","type":"char"},{"age":"1.1","code":23071,"gc":"Lo","kd":"beautiful, graceful","kc":"juān","kjo":"ken en","kjk":"adeyaka shinayaka kobiru","kk":"yen","ky":[23010],"name":"CJK UNIFIED IDEOGRAPH-5A1F","type":"char"},{"age":"1.1","code":23072,"gc":"Lo","kd":"pregnant","kc":"shēn xìn","kjo":"shin","kjk":"haramu","kk":"sin","ky":[14043],"name":"CJK UNIFIED IDEOGRAPH-5A20","type":"char"},{"age":"1.1","code":23073,"gc":"Lo","kc":"zhì","name":"CJK UNIFIED IDEOGRAPH-5A21","type":"char"},{"age":"1.1","code":23074,"gc":"Lo","kc":"hán","name":"CJK UNIFIED IDEOGRAPH-5A22","type":"char"},{"age":"1.1","code":23075,"gc":"Lo","kd":"younger sister, sister-in-law","kc":"dì","kjo":"tei dai","kjk":"imouto oba","kk":"cey","name":"CJK UNIFIED IDEOGRAPH-5A23","type":"char"},{"age":"1.1","code":23076,"gc":"Lo","kc":"zhuāng","kjo":"sou shou","kjk":"yosoou","name":"CJK UNIFIED IDEOGRAPH-5A24","type":"char"},{"age":"1.1","code":23077,"gc":"Lo","kd":"be beautiful; good; surname","kc":"é","kjo":"ga","kjk":"mimeyoi","kk":"a","kv":"nga","name":"CJK UNIFIED IDEOGRAPH-5A25","type":"char"},{"age":"1.1","code":23078,"gc":"Lo","kc":"pín","name":"CJK UNIFIED IDEOGRAPH-5A26","type":"char"},{"age":"1.1","code":23079,"gc":"Lo","kc":"tuì","kjo":"tai te etsu echi","kjk":"mimeyoi yorokobu","kk":"thay","name":"CJK UNIFIED IDEOGRAPH-5A27","type":"char"},{"age":"1.1","code":23080,"gc":"Lo","kc":"xiàn","kjo":"ban man kan gen","kjk":"gouman","name":"CJK UNIFIED IDEOGRAPH-5A28","type":"char"},{"age":"1.1","code":23081,"gc":"Lo","kd":"give birth child; complaisant","kc":"miǎn wǎn wèn","kjo":"ben han","kjk":"umu","kk":"man","ky":[14147],"name":"CJK UNIFIED IDEOGRAPH-5A29","type":"char"},{"age":"1.1","code":23082,"gc":"Lo","kc":"wú wù yú","kjo":"go gyo","kjk":"onna","name":"CJK UNIFIED IDEOGRAPH-5A2A","type":"char"},{"age":"1.1","code":23083,"gc":"Lo","kc":"yán","name":"CJK UNIFIED IDEOGRAPH-5A2B","type":"char"},{"age":"1.1","code":23084,"gc":"Lo","kd":"lovely; attractive","kc":"wǔ","kjo":"bu mu","kjk":"kobiru","ky":[23285],"name":"CJK UNIFIED IDEOGRAPH-5A2C","type":"char"},{"age":"1.1","code":23085,"gc":"Lo","kc":"xī āi","kjo":"ki ai","kjk":"tahomureru hashitame","kk":"ay","name":"CJK UNIFIED IDEOGRAPH-5A2D","type":"char"},{"age":"1.1","code":23086,"gc":"Lo","kc":"yán","kjo":"den","name":"CJK UNIFIED IDEOGRAPH-5A2E","type":"char"},{"age":"1.1","code":23087,"gc":"Lo","kd":"pleasure, enjoyment, amusement","kc":"yú","kjo":"go ku","kjk":"tanoshimu","kk":"o","ky":[23067],"name":"CJK UNIFIED IDEOGRAPH-5A2F","type":"char"},{"age":"1.1","code":23088,"gc":"Lo","kc":"sì","kjo":"ji shi","kjk":"ane","name":"CJK UNIFIED IDEOGRAPH-5A30","type":"char"},{"age":"1.1","code":23089,"gc":"Lo","kd":"pleasure, enjoyment, amusement","kc":"yú","ky":[23067],"name":"CJK UNIFIED IDEOGRAPH-5A31","type":"char"},{"age":"1.1","code":23090,"gc":"Lo","kd":"a goddess, the mythological sister and successor to Fuxi","kc":"wā","ky":[23207],"name":"CJK UNIFIED IDEOGRAPH-5A32","type":"char"},{"age":"1.1","code":23091,"gc":"Lo","kc":"lì","name":"CJK UNIFIED IDEOGRAPH-5A33","type":"char"},{"age":"1.1","code":23092,"gc":"Lo","kd":"elegant, refined; skillful","kc":"xián","ky":[23291],"name":"CJK UNIFIED IDEOGRAPH-5A34","type":"char"},{"age":"1.1","code":23093,"gc":"Lo","kd":"star","kc":"jū","kjo":"shu sou","kjk":"yome","kk":"chwu","name":"CJK UNIFIED IDEOGRAPH-5A35","type":"char"},{"age":"1.1","code":23094,"gc":"Lo","kd":"marry, take wife","kc":"qǔ jū shū","kjo":"shu","kjk":"metoru","kk":"chwi","kv":"thú","name":"CJK UNIFIED IDEOGRAPH-5A36","type":"char"},{"age":"1.1","code":23095,"gc":"Lo","kc":"zhuì shuì","kjo":"tsui sui zui","name":"CJK UNIFIED IDEOGRAPH-5A37","type":"char"},{"age":"1.1","code":23096,"gc":"Lo","kd":"ugly","kc":"qī","kjo":"ki","kjk":"minikui","name":"CJK UNIFIED IDEOGRAPH-5A38","type":"char"},{"age":"1.1","code":23097,"gc":"Lo","kc":"xián","kjo":"ken gen","name":"CJK UNIFIED IDEOGRAPH-5A39","type":"char"},{"age":"1.1","code":23098,"gc":"Lo","kc":"zhuó","name":"CJK UNIFIED IDEOGRAPH-5A3A","type":"char"},{"age":"1.1","code":23099,"gc":"Lo","kc":"dōng dòng","name":"CJK UNIFIED IDEOGRAPH-5A3B","type":"char"},{"age":"1.1","code":23100,"gc":"Lo","kd":"prostitute, harlot","kc":"chāng","kjo":"shou","kjk":"asobime","kk":"chang","name":"CJK UNIFIED IDEOGRAPH-5A3C","type":"char"},{"age":"1.1","code":23101,"gc":"Lo","kc":"lù","name":"CJK UNIFIED IDEOGRAPH-5A3D","type":"char"},{"age":"1.1","code":23102,"gc":"Lo","kc":"ǎi ái è","kjo":"gai ge gou kyou","kjk":"yorokobu mimeyoi","name":"CJK UNIFIED IDEOGRAPH-5A3E","type":"char"},{"age":"1.1","code":23103,"gc":"Lo","kc":"ē ě","kjo":"a","kjk":"sadamaranai shinayakanasama","kk":"a","ky":[23104],"name":"CJK UNIFIED IDEOGRAPH-5A3F","type":"char"},{"age":"1.1","code":23104,"gc":"Lo","kd":"be beautiful, be graceful","kc":"ě ē","kjo":"a","kjk":"taoyaka","kk":"a","ky":[23103],"name":"CJK UNIFIED IDEOGRAPH-5A40","type":"char"},{"age":"1.1","code":23105,"gc":"Lo","kd":"surname; a constellation; to wear","kc":"lóu lǚ lǘ léi","kjo":"rou ru rui","kjk":"munashii arai osameru","kk":"lwu","kv":"lâu","ky":[23044],"name":"CJK UNIFIED IDEOGRAPH-5A41","type":"char"},{"age":"1.1","code":23106,"gc":"Lo","kc":"mián","kjk":"ben men","name":"CJK UNIFIED IDEOGRAPH-5A42","type":"char"},{"age":"1.1","code":23107,"gc":"Lo","kc":"cóng","kjo":"sou su","name":"CJK UNIFIED IDEOGRAPH-5A43","type":"char"},{"age":"1.1","code":23108,"gc":"Lo","kd":"(Cant.) soft, weak; to soak; unreliable","kc":"pǒu péi bù","kjo":"hou bu bai","kjk":"oroka minikui","name":"CJK UNIFIED IDEOGRAPH-5A44","type":"char"},{"age":"1.1","code":23109,"gc":"Lo","kc":"jú","kjo":"kiku koku","kjk":"azana","name":"CJK UNIFIED IDEOGRAPH-5A45","type":"char"},{"age":"1.1","code":23110,"gc":"Lo","kd":"old woman; grandmother","kc":"pó po","kjo":"ba","kjk":"baba","kk":"pha","kv":"bà","name":"CJK UNIFIED IDEOGRAPH-5A46","type":"char"},{"age":"1.1","code":23111,"gc":"Lo","kc":"cǎi cāi","kjo":"sai","kjk":"uneme","name":"CJK UNIFIED IDEOGRAPH-5A47","type":"char"},{"age":"1.1","code":23112,"gc":"Lo","kc":"líng","kjo":"ryou","kjk":"azana","name":"CJK UNIFIED IDEOGRAPH-5A48","type":"char"},{"age":"1.1","code":23113,"gc":"Lo","kd":"amiable, congenial; restrained","kc":"wǎn","kjo":"en","kjk":"utsukushii","kk":"wan","kv":"uyển","name":"CJK UNIFIED IDEOGRAPH-5A49","type":"char"},{"age":"1.1","code":23114,"gc":"Lo","kd":"whore, prostitute","kc":"biǎo","kjo":"hyou","name":"CJK UNIFIED IDEOGRAPH-5A4A","type":"char"},{"age":"1.1","code":23115,"gc":"Lo","kc":"xiāo","name":"CJK UNIFIED IDEOGRAPH-5A4B","type":"char"},{"age":"1.1","code":23116,"gc":"Lo","kc":"shú","kjo":"shuku juku","kk":"swuk","name":"CJK UNIFIED IDEOGRAPH-5A4C","type":"char"},{"age":"1.1","code":23117,"gc":"Lo","kc":"qǐ","kjo":"ki","kjk":"mimeyoi","kv":"gả","name":"CJK UNIFIED IDEOGRAPH-5A4D","type":"char"},{"age":"1.1","code":23118,"gc":"Lo","kc":"huī","name":"CJK UNIFIED IDEOGRAPH-5A4E","type":"char"},{"age":"1.1","code":23119,"gc":"Lo","kc":"fù fàn","name":"CJK UNIFIED IDEOGRAPH-5A4F","type":"char"},{"age":"1.1","code":23120,"gc":"Lo","kd":"maid","kc":"wǒ","kjo":"wa ka","kjk":"taoyaka haberu","kk":"wa","name":"CJK UNIFIED IDEOGRAPH-5A50","type":"char"},{"age":"1.1","code":23121,"gc":"Lo","kc":"ruí wǒ něi","kjo":"zui ni wa","kjk":"haberu","name":"CJK UNIFIED IDEOGRAPH-5A51","type":"char"},{"age":"1.1","code":23122,"gc":"Lo","kc":"tán","kjo":"tan dan","name":"CJK UNIFIED IDEOGRAPH-5A52","type":"char"},{"age":"1.1","code":23123,"gc":"Lo","kc":"fēi","kjo":"hi","kjk":"samayou","name":"CJK UNIFIED IDEOGRAPH-5A53","type":"char"},{"age":"1.1","code":23124,"gc":"Lo","kc":"fēi","name":"CJK UNIFIED IDEOGRAPH-5A54","type":"char"},{"age":"1.1","code":23125,"gc":"Lo","kd":"handsome","kc":"jié qiè","kjo":"shou","kjk":"mimeyoi","name":"CJK UNIFIED IDEOGRAPH-5A55","type":"char"},{"age":"1.1","code":23126,"gc":"Lo","kc":"tiān","kjo":"ten","name":"CJK UNIFIED IDEOGRAPH-5A56","type":"char"},{"age":"1.1","code":23127,"gc":"Lo","kd":"a new-born child the whimper of an infant","kc":"ní nǐ","kjo":"gei","kjk":"midorigo akagononakigoe","name":"CJK UNIFIED IDEOGRAPH-5A57","type":"char"},{"age":"1.1","code":23128,"gc":"Lo","kc":"quán juàn","kjo":"ken gen","kjk":"mimeyoi yakari","name":"CJK UNIFIED IDEOGRAPH-5A58","type":"char"},{"age":"1.1","code":23129,"gc":"Lo","kc":"jìng","name":"CJK UNIFIED IDEOGRAPH-5A59","type":"char"},{"age":"1.1","code":23130,"gc":"Lo","kd":"get married; marriage, wedding","kc":"hūn","kjo":"kon","kjk":"engumi","kk":"hon","name":"CJK UNIFIED IDEOGRAPH-5A5A","type":"char"},{"age":"1.1","code":23131,"gc":"Lo","kc":"jīng","kjo":"kei kyou","name":"CJK UNIFIED IDEOGRAPH-5A5B","type":"char"},{"age":"1.1","code":23132,"gc":"Lo","kc":"qiān jǐn","kjo":"kan ken kin","kjk":"utsukushii","name":"CJK UNIFIED IDEOGRAPH-5A5C","type":"char"},{"age":"1.1","code":23133,"gc":"Lo","kc":"diàn","kjo":"ten den","name":"CJK UNIFIED IDEOGRAPH-5A5D","type":"char"},{"age":"1.1","code":23134,"gc":"Lo","kd":"hate","kc":"xìng","kjo":"kei gyou kou","kjk":"motoru matsusugu","name":"CJK UNIFIED IDEOGRAPH-5A5E","type":"char"},{"age":"1.1","code":23135,"gc":"Lo","kc":"hù","kjo":"ko go","kjk":"koishitau oshimu yoi","name":"CJK UNIFIED IDEOGRAPH-5A5F","type":"char"},{"age":"1.1","code":23136,"gc":"Lo","kc":"wān guàn","kjo":"wan watsu wachi kan kuwatsu guwachi","kjk":"shinayoi mimeyoisama","name":"CJK UNIFIED IDEOGRAPH-5A60","type":"char"},{"age":"1.1","code":23137,"gc":"Lo","kc":"lái lài","name":"CJK UNIFIED IDEOGRAPH-5A61","type":"char"},{"age":"1.1","code":23138,"gc":"Lo","kd":"servant girl; your servant","kc":"bì","kjo":"hi","kjk":"hashitame","kk":"pi","kv":"tì","name":"CJK UNIFIED IDEOGRAPH-5A62","type":"char"},{"age":"1.1","code":23139,"gc":"Lo","kd":"marriage connections, a bride","kc":"yīn","kjo":"in","kk":"in","ky":[23035],"name":"CJK UNIFIED IDEOGRAPH-5A63","type":"char"},{"age":"1.1","code":23140,"gc":"Lo","kd":"lovely","kc":"zhōu chōu","kjo":"shuu shu chou chuu juu","kjk":"mimeyoisama","name":"CJK UNIFIED IDEOGRAPH-5A64","type":"char"},{"age":"1.1","code":23141,"gc":"Lo","kd":"beautiful","kc":"nào chuò","kjo":"dou nyou teki jaku shaku","kjk":"mimeyoi","name":"CJK UNIFIED IDEOGRAPH-5A65","type":"char"},{"age":"1.1","code":23142,"gc":"Lo","kd":"married women; woman; wife","kc":"fù fu","kjo":"fu","kjk":"yome onna","kk":"pwu","kv":"phụ","ky":[22919,23181],"name":"CJK UNIFIED IDEOGRAPH-5A66","type":"char"},{"age":"1.1","code":23143,"gc":"Lo","kd":"modest; supple","kc":"jìng","kjo":"sei shou juu","kjk":"ateyakanasama shinayaka","kk":"ceng","name":"CJK UNIFIED IDEOGRAPH-5A67","type":"char"},{"age":"1.1","code":23144,"gc":"Lo","kc":"lún","name":"CJK UNIFIED IDEOGRAPH-5A68","type":"char"},{"age":"1.1","code":23145,"gc":"Lo","kc":"àn nüè","kjo":"gen gan jaku gaku","kjk":"totonou mimeyoi mutsutsurisuru","name":"CJK UNIFIED IDEOGRAPH-5A69","type":"char"},{"age":"1.1","code":23146,"gc":"Lo","kd":"covet; covetous, avaricious","kc":"lán lǎn","kjo":"ran rin","kjk":"musaboru","kk":"lam","kv":"lam","name":"CJK UNIFIED IDEOGRAPH-5A6A","type":"char"},{"age":"1.1","code":23147,"gc":"Lo","kc":"kūn hùn","name":"CJK UNIFIED IDEOGRAPH-5A6B","type":"char"},{"age":"1.1","code":23148,"gc":"Lo","kd":"obscene, licentious, lewd","kc":"yín yàn yáo","kjo":"in","kjk":"tawakeru midari","kk":"um","kv":"dâm","ky":[28139],"name":"CJK UNIFIED IDEOGRAPH-5A6C","type":"char"},{"age":"1.1","code":23149,"gc":"Lo","kd":"mutual term of address used by sons-in-law; a brother-in-law","kc":"yà yā yǎ","kjo":"a","kjk":"aimuko koshimoto","kv":"ả","ky":[23045],"name":"CJK UNIFIED IDEOGRAPH-5A6D","type":"char"},{"age":"1.1","code":23150,"gc":"Lo","kc":"jū","name":"CJK UNIFIED IDEOGRAPH-5A6E","type":"char"},{"age":"1.1","code":23151,"gc":"Lo","kc":"lì","name":"CJK UNIFIED IDEOGRAPH-5A6F","type":"char"},{"age":"1.1","code":23152,"gc":"Lo","kc":"diǎn","kjo":"ten","name":"CJK UNIFIED IDEOGRAPH-5A70","type":"char"},{"age":"1.1","code":23153,"gc":"Lo","kc":"xián","name":"CJK UNIFIED IDEOGRAPH-5A71","type":"char"},{"age":"1.1","code":23154,"gc":"Lo","kc":"huā","kk":"hwa","name":"CJK UNIFIED IDEOGRAPH-5A72","type":"char"},{"age":"1.1","code":23155,"gc":"Lo","kd":"tranquil","kc":"huà","kjo":"kaku gyaku","kjk":"shitoyaka mimeyoi","ky":[23295],"name":"CJK UNIFIED IDEOGRAPH-5A73","type":"char"},{"age":"1.1","code":23156,"gc":"Lo","kd":"baby, infant; bother","kc":"yīng yìng","ky":[23344],"name":"CJK UNIFIED IDEOGRAPH-5A74","type":"char"},{"age":"1.1","code":23157,"gc":"Lo","kd":"beautiful, lovely, pretty, graceful","kc":"chán","ky":[23307],"name":"CJK UNIFIED IDEOGRAPH-5A75","type":"char"},{"age":"1.1","code":23158,"gc":"Lo","kd":"wife of father's younger brother","kc":"shěn shen","ky":[23352],"name":"CJK UNIFIED IDEOGRAPH-5A76","type":"char"},{"age":"1.1","code":23159,"gc":"Lo","kd":"pretty; attractive; graceful","kc":"tíng","kjo":"tei chou","kjk":"utsukushii","kk":"ceng","name":"CJK UNIFIED IDEOGRAPH-5A77","type":"char"},{"age":"1.1","code":23160,"gc":"Lo","kc":"dàng yáng","kjo":"tou dou you","kjk":"midara tawamurerusama wawa","name":"CJK UNIFIED IDEOGRAPH-5A78","type":"char"},{"age":"1.1","code":23161,"gc":"Lo","kc":"yǎo","name":"CJK UNIFIED IDEOGRAPH-5A79","type":"char"},{"age":"1.1","code":23162,"gc":"Lo","kd":"name of a star","kc":"wù móu mù","kjo":"bu mu bou boku moku","name":"CJK UNIFIED IDEOGRAPH-5A7A","type":"char"},{"age":"1.1","code":23163,"gc":"Lo","kc":"nàn","kjo":"dan nan","kjk":"utsukushii","name":"CJK UNIFIED IDEOGRAPH-5A7B","type":"char"},{"age":"1.1","code":23164,"gc":"Lo","kd":"person","kc":"chuò ruò","kjo":"shaku ji ni ja nyuu","name":"CJK UNIFIED IDEOGRAPH-5A7C","type":"char"},{"age":"1.1","code":23165,"gc":"Lo","kc":"jiǎ","kjo":"ka ke","kjk":"mimeyoi","name":"CJK UNIFIED IDEOGRAPH-5A7D","type":"char"},{"age":"1.1","code":23166,"gc":"Lo","kd":"handsome","kc":"tōu yú","kjo":"tou tsu yu","kjk":"warugashikoi nusumu gomakasu","ky":[23214],"name":"CJK UNIFIED IDEOGRAPH-5A7E","type":"char"},{"age":"1.1","code":23167,"gc":"Lo","kd":"son-in-law; husband","kc":"xù","kjo":"sei","kjk":"muko","kk":"se","ky":[22779,32863],"name":"CJK UNIFIED IDEOGRAPH-5A7F","type":"char"},{"age":"1.1","code":23168,"gc":"Lo","kc":"yù yú","name":"CJK UNIFIED IDEOGRAPH-5A80","type":"char"},{"age":"1.1","code":23169,"gc":"Lo","kc":"wéi wěi","name":"CJK UNIFIED IDEOGRAPH-5A81","type":"char"},{"age":"1.1","code":23170,"gc":"Lo","kc":"dì tí","name":"CJK UNIFIED IDEOGRAPH-5A82","type":"char"},{"age":"1.1","code":23171,"gc":"Lo","kc":"róu","kjo":"juu nyu","name":"CJK UNIFIED IDEOGRAPH-5A83","type":"char"},{"age":"1.1","code":23172,"gc":"Lo","kd":"beautiful","kc":"měi","kjo":"bi mi","kjk":"mimeyoi","kk":"mi","kv":"mẹ","name":"CJK UNIFIED IDEOGRAPH-5A84","type":"char"},{"age":"1.1","code":23173,"gc":"Lo","kc":"dān","name":"CJK UNIFIED IDEOGRAPH-5A85","type":"char"},{"age":"1.1","code":23174,"gc":"Lo","kd":"young, tender, soft, delicate","kc":"ruǎn nèn nùn","ky":[23273],"name":"CJK UNIFIED IDEOGRAPH-5A86","type":"char"},{"age":"1.1","code":23175,"gc":"Lo","kc":"qīn","name":"CJK UNIFIED IDEOGRAPH-5A87","type":"char"},{"age":"1.1","code":23176,"gc":"Lo","kc":"huī","name":"CJK UNIFIED IDEOGRAPH-5A88","type":"char"},{"age":"1.1","code":23177,"gc":"Lo","kc":"wò","name":"CJK UNIFIED IDEOGRAPH-5A89","type":"char"},{"age":"1.1","code":23178,"gc":"Lo","kd":"star","kc":"qián","kjo":"sen zen shi","name":"CJK UNIFIED IDEOGRAPH-5A8A","type":"char"},{"age":"1.1","code":23179,"gc":"Lo","kc":"chūn","kjo":"shun","kjk":"utsukushii","name":"CJK UNIFIED IDEOGRAPH-5A8B","type":"char"},{"age":"1.1","code":23180,"gc":"Lo","kc":"miáo","kjo":"bou myou boku moku","kjk":"mimeyoi","name":"CJK UNIFIED IDEOGRAPH-5A8C","type":"char"},{"age":"1.1","code":23181,"gc":"Lo","kd":"woman, wife","kc":"fù fu","kk":"pwu","ky":[23142],"name":"CJK UNIFIED IDEOGRAPH-5A8D","type":"char"},{"age":"1.1","code":23182,"gc":"Lo","kc":"jiě","kjo":"so","kv":"chửa","name":"CJK UNIFIED IDEOGRAPH-5A8E","type":"char"},{"age":"1.1","code":23183,"gc":"Lo","kc":"duān","kjo":"tan","name":"CJK UNIFIED IDEOGRAPH-5A8F","type":"char"},{"age":"1.1","code":23184,"gc":"Lo","kc":"yí xī","kjo":"ki i","kjk":"tsuma tanoshimu","name":"CJK UNIFIED IDEOGRAPH-5A90","type":"char"},{"age":"1.1","code":23185,"gc":"Lo","kc":"zhòng","name":"CJK UNIFIED IDEOGRAPH-5A91","type":"char"},{"age":"1.1","code":23186,"gc":"Lo","kd":"go-between, matchmaker; medium","kc":"méi mèi","kjo":"bai mai bou","kjk":"nakoudo","kk":"may","kv":"mối","name":"CJK UNIFIED IDEOGRAPH-5A92","type":"char"},{"age":"1.1","code":23187,"gc":"Lo","kc":"huáng","kjo":"kou ou","kjk":"haha","kk":"hwang","name":"CJK UNIFIED IDEOGRAPH-5A93","type":"char"},{"age":"1.1","code":23188,"gc":"Lo","kc":"mián miǎn","kjo":"ben men","kjk":"netamu","name":"CJK UNIFIED IDEOGRAPH-5A94","type":"char"},{"age":"1.1","code":23189,"gc":"Lo","kd":"undecided","kc":"yǎn è ān","kjo":"en an on au ou","kk":"am","name":"CJK UNIFIED IDEOGRAPH-5A95","type":"char"},{"age":"1.1","code":23190,"gc":"Lo","kd":"beauty; beautiful","kc":"yīng","kjo":"ei yuu","name":"CJK UNIFIED IDEOGRAPH-5A96","type":"char"},{"age":"1.1","code":23191,"gc":"Lo","kc":"xuān","kjo":"ken kan sen","name":"CJK UNIFIED IDEOGRAPH-5A97","type":"char"},{"age":"1.1","code":23192,"gc":"Lo","kc":"jiē","name":"CJK UNIFIED IDEOGRAPH-5A98","type":"char"},{"age":"1.1","code":23193,"gc":"Lo","kc":"wēi","kjo":"i","kjk":"utsukushii","name":"CJK UNIFIED IDEOGRAPH-5A99","type":"char"},{"age":"1.1","code":23194,"gc":"Lo","kd":"charming, attractive; flatter","kc":"mèi","kjo":"bi","kjk":"kobiru","kk":"mi","name":"CJK UNIFIED IDEOGRAPH-5A9A","type":"char"},{"age":"1.1","code":23195,"gc":"Lo","kd":"beauty, beautiful woman","kc":"yuàn yuán","kjo":"en","kjk":"hime","kk":"wen","name":"CJK UNIFIED IDEOGRAPH-5A9B","type":"char"},{"age":"1.1","code":23196,"gc":"Lo","kc":"zhēng","kjo":"tei chou","kjk":"azana","name":"CJK UNIFIED IDEOGRAPH-5A9C","type":"char"},{"age":"1.1","code":23197,"gc":"Lo","kc":"qiū","kjo":"shuu shu","name":"CJK UNIFIED IDEOGRAPH-5A9D","type":"char"},{"age":"1.1","code":23198,"gc":"Lo","kd":"at ease","kc":"shì tí zhī dài","kjo":"shi ji tei dai tai ta","kjk":"tsumabiraka warugashikoi haha","name":"CJK UNIFIED IDEOGRAPH-5A9E","type":"char"},{"age":"1.1","code":23199,"gc":"Lo","kd":"lust after, act indecently; lewd","kc":"xiè","kjo":"setsu sechi","kjk":"kegasu kegareru nareru anadoru","kk":"sel","name":"CJK UNIFIED IDEOGRAPH-5A9F","type":"char"},{"age":"1.1","code":23200,"gc":"Lo","kc":"tuǒ duò nuǒ","kjo":"ta da na ra","kjk":"mimeyoi okotaru mimeyoisama","name":"CJK UNIFIED IDEOGRAPH-5AA0","type":"char"},{"age":"1.1","code":23201,"gc":"Lo","kc":"liàn","name":"CJK UNIFIED IDEOGRAPH-5AA1","type":"char"},{"age":"1.1","code":23202,"gc":"Lo","kd":"be jealous of, be envious","kc":"mào","kjo":"bou mou boku moku bai me","kjk":"netamu niramu","kk":"mo","name":"CJK UNIFIED IDEOGRAPH-5AA2","type":"char"},{"age":"1.1","code":23203,"gc":"Lo","kc":"rǎn","name":"CJK UNIFIED IDEOGRAPH-5AA3","type":"char"},{"age":"1.1","code":23204,"gc":"Lo","kd":"husband's family","kc":"sī","kjo":"shi","kk":"si","name":"CJK UNIFIED IDEOGRAPH-5AA4","type":"char"},{"age":"1.1","code":23205,"gc":"Lo","kc":"piān","kjo":"hen","name":"CJK UNIFIED IDEOGRAPH-5AA5","type":"char"},{"age":"1.1","code":23206,"gc":"Lo","kc":"wèi","kjo":"i","kjk":"imouto","name":"CJK UNIFIED IDEOGRAPH-5AA6","type":"char"},{"age":"1.1","code":23207,"gc":"Lo","kd":"mythological snail goddess","kc":"wā","kjo":"kai ke ka","kk":"way kwa","kv":"oa","ky":[23090],"name":"CJK UNIFIED IDEOGRAPH-5AA7","type":"char"},{"age":"1.1","code":23208,"gc":"Lo","kc":"cù","name":"CJK UNIFIED IDEOGRAPH-5AA8","type":"char"},{"age":"1.1","code":23209,"gc":"Lo","kc":"hú","kjo":"ko go","name":"CJK UNIFIED IDEOGRAPH-5AA9","type":"char"},{"age":"1.1","code":23210,"gc":"Lo","kd":"old woman; lower-class woman","kc":"ǎo yǔn wò","kjo":"ou","kjk":"ouna","kk":"o","ky":[23228],"name":"CJK UNIFIED IDEOGRAPH-5AAA","type":"char"},{"age":"1.1","code":23211,"gc":"Lo","kc":"jié","name":"CJK UNIFIED IDEOGRAPH-5AAB","type":"char"},{"age":"1.1","code":23212,"gc":"Lo","kd":"governess; nurse","kc":"bǎo","kjo":"ho","name":"CJK UNIFIED IDEOGRAPH-5AAC","type":"char"},{"age":"1.1","code":23213,"gc":"Lo","kc":"xū","kjo":"shu","kjk":"ane","ky":[23299],"name":"CJK UNIFIED IDEOGRAPH-5AAD","type":"char"},{"age":"1.1","code":23214,"gc":"Lo","kd":"handsome, cheerful; steal","kc":"tōu yú","kjo":"tou tsu yu","kjk":"warugashikoi nusumu gomakasu","ky":[23166],"name":"CJK UNIFIED IDEOGRAPH-5AAE","type":"char"},{"age":"1.1","code":23215,"gc":"Lo","kd":"family name","kc":"guī guì","ky":[22955,23296],"name":"CJK UNIFIED IDEOGRAPH-5AAF","type":"char"},{"age":"1.1","code":23216,"gc":"Lo","kc":"chú zòu","kjo":"shiu su shu ju","kjk":"haramu mimeyoi yamome","ky":[14016],"name":"CJK UNIFIED IDEOGRAPH-5AB0","type":"char"},{"age":"1.1","code":23217,"gc":"Lo","kc":"yáo","kjo":"eu","kjk":"mimeyoi tahamureru","name":"CJK UNIFIED IDEOGRAPH-5AB1","type":"char"},{"age":"1.1","code":23218,"gc":"Lo","kd":"marry off, pair, match; compare","kc":"pì bī pí","kjo":"hei hi bi","kjk":"tsureahi","name":"CJK UNIFIED IDEOGRAPH-5AB2","type":"char"},{"age":"1.1","code":23219,"gc":"Lo","kd":"daughter-in-law","kc":"xí","kjo":"seki shaku","kjk":"yome","kk":"sik","name":"CJK UNIFIED IDEOGRAPH-5AB3","type":"char"},{"age":"1.1","code":23220,"gc":"Lo","kc":"yuán","kjo":"en on","name":"CJK UNIFIED IDEOGRAPH-5AB4","type":"char"},{"age":"1.1","code":23221,"gc":"Lo","kd":"a maid who accompanies bride to her new home; to escort; a concubine","kc":"yìng shèng","kjo":"you","kjk":"okuru tsukisohi okurime okuribito","kk":"ing","name":"CJK UNIFIED IDEOGRAPH-5AB5","type":"char"},{"age":"1.1","code":23222,"gc":"Lo","kc":"róng","kjo":"jou nyu","name":"CJK UNIFIED IDEOGRAPH-5AB6","type":"char"},{"age":"1.1","code":23223,"gc":"Lo","kc":"rù","kjo":"joku niku","kjk":"okotaru","name":"CJK UNIFIED IDEOGRAPH-5AB7","type":"char"},{"age":"1.1","code":23224,"gc":"Lo","kd":"an ugly woman","kc":"chī","kjo":"shi","kjk":"anadoru oroka minikui midaru","name":"CJK UNIFIED IDEOGRAPH-5AB8","type":"char"},{"age":"1.1","code":23225,"gc":"Lo","kc":"liú","kjo":"riu ru","name":"CJK UNIFIED IDEOGRAPH-5AB9","type":"char"},{"age":"1.1","code":23226,"gc":"Lo","kd":"beautiful","kc":"měi","kjo":"bi mi","kjk":"yoi utsukushii","kk":"mi","name":"CJK UNIFIED IDEOGRAPH-5ABA","type":"char"},{"age":"1.1","code":23227,"gc":"Lo","kd":"to move","kc":"pán","kjo":"han ban ha ba","kjk":"ogoru mekake yoromeku","kk":"pan","name":"CJK UNIFIED IDEOGRAPH-5ABB","type":"char"},{"age":"1.1","code":23228,"gc":"Lo","kd":"old woman; lower-class woman","kc":"ǎo yǔn wò","kjo":"ou","kjk":"ouna","kk":"on","ky":[23210],"name":"CJK UNIFIED IDEOGRAPH-5ABC","type":"char"},{"age":"1.1","code":23229,"gc":"Lo","kd":"mother, mama","kc":"mā ma","kjo":"bo mo","kjk":"haha","kk":"ma","kv":"má","ky":[22920],"name":"CJK UNIFIED IDEOGRAPH-5ABD","type":"char"},{"age":"1.1","code":23230,"gc":"Lo","kd":"marry; be on friendly terms with","kc":"gòu","kjo":"kou","kjk":"yoshimi","kk":"kwu","name":"CJK UNIFIED IDEOGRAPH-5ABE","type":"char"},{"age":"1.1","code":23231,"gc":"Lo","kd":"ashamed, conscience-stricken","kc":"kuì chǒu","kjo":"ki","kjk":"hajiru hazukashimeru togameru","kk":"koy","ky":[24871],"name":"CJK UNIFIED IDEOGRAPH-5ABF","type":"char"},{"age":"1.1","code":23232,"gc":"Lo","kc":"qín shēn","kjo":"shin jin","name":"CJK UNIFIED IDEOGRAPH-5AC0","type":"char"},{"age":"1.1","code":23233,"gc":"Lo","kd":"to marry, give a daughter in marriage","kc":"jià","kjo":"ka ke","kjk":"totsugu yome","kk":"ka","kv":"giá","name":"CJK UNIFIED IDEOGRAPH-5AC1","type":"char"},{"age":"1.1","code":23234,"gc":"Lo","kd":"sister-in-law, elder brother's wife","kc":"sǎo sao","kjo":"sou","kjk":"anyome","kk":"swu","kv":"dâu","name":"CJK UNIFIED IDEOGRAPH-5AC2","type":"char"},{"age":"1.1","code":23235,"gc":"Lo","kc":"zhēn zhěn","name":"CJK UNIFIED IDEOGRAPH-5AC3","type":"char"},{"age":"1.1","code":23236,"gc":"Lo","kd":"an ancient emperor's mother's name, Qiang Yuan, consort to Gu","kc":"yuán","kjo":"gen gan","kk":"wen","name":"CJK UNIFIED IDEOGRAPH-5AC4","type":"char"},{"age":"1.1","code":23237,"gc":"Lo","kc":"jiē suǒ","name":"CJK UNIFIED IDEOGRAPH-5AC5","type":"char"},{"age":"1.1","code":23238,"gc":"Lo","kc":"róng","kjo":"you yu","kjk":"azana","name":"CJK UNIFIED IDEOGRAPH-5AC6","type":"char"},{"age":"1.1","code":23239,"gc":"Lo","kc":"míng mǐng méng","kjo":"bei myau bau","kjk":"ozuozutosuru","name":"CJK UNIFIED IDEOGRAPH-5AC7","type":"char"},{"age":"1.1","code":23240,"gc":"Lo","kd":"lady","kc":"yīng xīng yíng","kjo":"seu au gei gyou ei kei","kjk":"mimeyoisama minikui mimeyoisugata","kk":"ayng","name":"CJK UNIFIED IDEOGRAPH-5AC8","type":"char"},{"age":"1.1","code":23241,"gc":"Lo","kd":"jealousy; be jealous of","kc":"jí jì","kjo":"shitsu","kjk":"netamu nikumu","kk":"cil","ky":[137009],"name":"CJK UNIFIED IDEOGRAPH-5AC9","type":"char"},{"age":"1.1","code":23242,"gc":"Lo","kc":"sù","kjo":"so","name":"CJK UNIFIED IDEOGRAPH-5ACA","type":"char"},{"age":"1.1","code":23243,"gc":"Lo","kd":"slender and delicate","kc":"niǎo","kjo":"jou jaku deki","kjk":"taoyaka shinayaka","kk":"nyo yak","ky":[23325],"name":"CJK UNIFIED IDEOGRAPH-5ACB","type":"char"},{"age":"1.1","code":23244,"gc":"Lo","kd":"hate, detest; suspect; criticize","kc":"xián","kjo":"ken gen","kjk":"kirau utagau","kk":"hyem","kv":"hiềm","name":"CJK UNIFIED IDEOGRAPH-5ACC","type":"char"},{"age":"1.1","code":23245,"gc":"Lo","kc":"tāo","kjo":"tau tou eu","name":"CJK UNIFIED IDEOGRAPH-5ACD","type":"char"},{"age":"1.1","code":23246,"gc":"Lo","kc":"páng bàng","name":"CJK UNIFIED IDEOGRAPH-5ACE","type":"char"},{"age":"1.1","code":23247,"gc":"Lo","kd":"the place where the supreme stores his books; library","kc":"láng","kjo":"rou","name":"CJK UNIFIED IDEOGRAPH-5ACF","type":"char"},{"age":"1.1","code":23248,"gc":"Lo","kd":"frolic, play with; flirt with","kc":"nǎo nán nǎn nàn","kjo":"jou","kjk":"naburu","ky":[21891],"name":"CJK UNIFIED IDEOGRAPH-5AD0","type":"char"},{"age":"1.1","code":23249,"gc":"Lo","kc":"báo","name":"CJK UNIFIED IDEOGRAPH-5AD1","type":"char"},{"age":"1.1","code":23250,"gc":"Lo","kd":"(your) daughter","kc":"ài","ky":[23329],"name":"CJK UNIFIED IDEOGRAPH-5AD2","type":"char"},{"age":"1.1","code":23251,"gc":"Lo","kc":"pì","name":"CJK UNIFIED IDEOGRAPH-5AD3","type":"char"},{"age":"1.1","code":23252,"gc":"Lo","kd":"court lady; palace maid","kc":"pín","ky":[23338],"name":"CJK UNIFIED IDEOGRAPH-5AD4","type":"char"},{"age":"1.1","code":23253,"gc":"Lo","kd":"compliant, yielding; easy-going","kc":"yì yī","kjo":"ei","kjk":"shitoyaka sunaho","ky":[23259],"name":"CJK UNIFIED IDEOGRAPH-5AD5","type":"char"},{"age":"1.1","code":23254,"gc":"Lo","kd":"patronize prostitutes, frequent","kc":"piào piáo biāo","kjo":"hyou","kjk":"karui","kk":"phyo","kv":"phếu","name":"CJK UNIFIED IDEOGRAPH-5AD6","type":"char"},{"age":"1.1","code":23255,"gc":"Lo","kd":"old woman, hag","kc":"yù yǔ kōu","kjo":"ou u","kjk":"ouna atatameru","kk":"kwu","kv":"ẩu","ky":[22954],"name":"CJK UNIFIED IDEOGRAPH-5AD7","type":"char"},{"age":"1.1","code":23256,"gc":"Lo","kd":"surname","kc":"léi","kjo":"rui rai re","name":"CJK UNIFIED IDEOGRAPH-5AD8","type":"char"},{"age":"1.1","code":23257,"gc":"Lo","kc":"xuán","kjo":"sen zen","kjk":"mimeyoi","kk":"sen","name":"CJK UNIFIED IDEOGRAPH-5AD9","type":"char"},{"age":"1.1","code":23258,"gc":"Lo","kd":"scorn, despise; be rude, affront","kc":"màn yuān mān","kjo":"ban man ben men en","kjk":"anadoru kegasu okotaru ogoru","kk":"man","name":"CJK UNIFIED IDEOGRAPH-5ADA","type":"char"},{"age":"1.1","code":23259,"gc":"Lo","kd":"compliant, yielding; easy-going a newborn child","kc":"yī yì","kjo":"ei i","kjk":"midorigo sunaho","kk":"yey","ky":[23253],"name":"CJK UNIFIED IDEOGRAPH-5ADB","type":"char"},{"age":"1.1","code":23260,"gc":"Lo","kc":"zhāng","kjo":"shau","kjk":"shiuto shiutome","name":"CJK UNIFIED IDEOGRAPH-5ADC","type":"char"},{"age":"1.1","code":23261,"gc":"Lo","kc":"kāng","kjo":"kau","name":"CJK UNIFIED IDEOGRAPH-5ADD","type":"char"},{"age":"1.1","code":23262,"gc":"Lo","kc":"yōng","kjo":"shou ju chou chu","name":"CJK UNIFIED IDEOGRAPH-5ADE","type":"char"},{"age":"1.1","code":23263,"gc":"Lo","kc":"nì","kjo":"jiyuku niki","kjk":"midara","name":"CJK UNIFIED IDEOGRAPH-5ADF","type":"char"},{"age":"1.1","code":23264,"gc":"Lo","kd":"a widow","kc":"lí","kjo":"ri","kjk":"yamome","kk":"li","name":"CJK UNIFIED IDEOGRAPH-5AE0","type":"char"},{"age":"1.1","code":23265,"gc":"Lo","kd":"legal wife, child of legal wife","kc":"dí","kjo":"chaku teki","kjk":"yotsugi","kk":"cek","kv":"đích","name":"CJK UNIFIED IDEOGRAPH-5AE1","type":"char"},{"age":"1.1","code":23266,"gc":"Lo","kc":"guī zuī","kjo":"ki i gi shi ken gen","kjk":"akiraka shinayaka taoyaka","kk":"kyu","name":"CJK UNIFIED IDEOGRAPH-5AE2","type":"char"},{"age":"1.1","code":23267,"gc":"Lo","kd":"charming, fascinating; gay","kc":"yān","kjo":"en","kk":"en","name":"CJK UNIFIED IDEOGRAPH-5AE3","type":"char"},{"age":"1.1","code":23268,"gc":"Lo","kc":"jǐn jìn","name":"CJK UNIFIED IDEOGRAPH-5AE4","type":"char"},{"age":"1.1","code":23269,"gc":"Lo","kc":"zhuān tuán","kjo":"sen tan dan","kjk":"motsupara totonoheru","kk":"cen","name":"CJK UNIFIED IDEOGRAPH-5AE5","type":"char"},{"age":"1.1","code":23270,"gc":"Lo","kd":"name of a moon goddess","kc":"cháng","kjo":"kou gou","kk":"hang","kv":"thường","name":"CJK UNIFIED IDEOGRAPH-5AE6","type":"char"},{"age":"1.1","code":23271,"gc":"Lo","kc":"zé cè","name":"CJK UNIFIED IDEOGRAPH-5AE7","type":"char"},{"age":"1.1","code":23272,"gc":"Lo","kc":"hān nǎn","kjo":"kan zen nen","kjk":"ikaru tsutsushimu","name":"CJK UNIFIED IDEOGRAPH-5AE8","type":"char"},{"age":"1.1","code":23273,"gc":"Lo","kd":"soft, tender, delicate; young","kc":"nèn ruǎn nùn","kjo":"don non zen","kjk":"wakai","kk":"nwun","kv":"non","ky":[137150,23174],"name":"CJK UNIFIED IDEOGRAPH-5AE9","type":"char"},{"age":"1.1","code":23274,"gc":"Lo","kd":"hanker","kc":"lào láo","kjo":"rau rou","kjk":"kohishitahu nayamu","name":"CJK UNIFIED IDEOGRAPH-5AEA","type":"char"},{"age":"1.1","code":23275,"gc":"Lo","kd":"Huangdi's ugly concubine; nurse","kc":"mó mā","kjo":"bo mo","kjk":"shikome","kk":"mo","ky":[23351],"name":"CJK UNIFIED IDEOGRAPH-5AEB","type":"char"},{"age":"1.1","code":23276,"gc":"Lo","kc":"zhē","kjo":"sha sho","name":"CJK UNIFIED IDEOGRAPH-5AEC","type":"char"},{"age":"1.1","code":23277,"gc":"Lo","kc":"hù","kjo":"ko go","kjk":"otome mimeyoisama netamu","kk":"ho","name":"CJK UNIFIED IDEOGRAPH-5AED","type":"char"},{"age":"1.1","code":23278,"gc":"Lo","kc":"hù","kjo":"ko go","kjk":"otome mimeyoisama hokoru","kk":"ho","name":"CJK UNIFIED IDEOGRAPH-5AEE","type":"char"},{"age":"1.1","code":23279,"gc":"Lo","kc":"ào","kk":"o","name":"CJK UNIFIED IDEOGRAPH-5AEF","type":"char"},{"age":"1.1","code":23280,"gc":"Lo","kd":"tender, delicate, soft","kc":"nèn","name":"CJK UNIFIED IDEOGRAPH-5AF0","type":"char"},{"age":"1.1","code":23281,"gc":"Lo","kd":"lady","kc":"qiáng","ky":[23321],"name":"CJK UNIFIED IDEOGRAPH-5AF1","type":"char"},{"age":"1.1","code":23282,"gc":"Lo","kd":"(Cant.) paternal grandmother","kc":"ma","name":"CJK UNIFIED IDEOGRAPH-5AF2","type":"char"},{"age":"1.1","code":23283,"gc":"Lo","kc":"piè","kjo":"hetsu hechi","kjk":"okoru karuisama","name":"CJK UNIFIED IDEOGRAPH-5AF3","type":"char"},{"age":"1.1","code":23284,"gc":"Lo","kc":"gū","kjo":"ko ku","kjk":"makaseru shibaraku hakaru suuberu","name":"CJK UNIFIED IDEOGRAPH-5AF4","type":"char"},{"age":"1.1","code":23285,"gc":"Lo","kd":"charming, enchanting","kc":"wǔ","kjo":"bu mu","kjk":"kobiru mimeyoi","ky":[22953,23084],"name":"CJK UNIFIED IDEOGRAPH-5AF5","type":"char"},{"age":"1.1","code":23286,"gc":"Lo","kc":"qiáo jiāo","kjo":"seu zeu","kjk":"yatsureru","kk":"cho","name":"CJK UNIFIED IDEOGRAPH-5AF6","type":"char"},{"age":"1.1","code":23287,"gc":"Lo","kc":"tuǒ","kjo":"ta","kjk":"mimeyoi utsukushii","name":"CJK UNIFIED IDEOGRAPH-5AF7","type":"char"},{"age":"1.1","code":23288,"gc":"Lo","kc":"zhǎn","kjo":"sen","kjk":"hazukashimeru katakuna","name":"CJK UNIFIED IDEOGRAPH-5AF8","type":"char"},{"age":"1.1","code":23289,"gc":"Lo","kc":"miáo","kjo":"bau meu","kjk":"mimeyoisama","name":"CJK UNIFIED IDEOGRAPH-5AF9","type":"char"},{"age":"1.1","code":23290,"gc":"Lo","kd":"refined, elegant, gracious","kc":"xián","kjo":"kan","kjk":"miyabiyaka","kk":"han","ky":[23291],"name":"CJK UNIFIED IDEOGRAPH-5AFA","type":"char"},{"age":"1.1","code":23291,"gc":"Lo","kd":"elegant, refined; skillful","kc":"xián","kjo":"kan","kjk":"miyabiyaka","kk":"han","ky":[23092,23290],"name":"CJK UNIFIED IDEOGRAPH-5AFB","type":"char"},{"age":"1.1","code":23292,"gc":"Lo","kc":"mò","name":"CJK UNIFIED IDEOGRAPH-5AFC","type":"char"},{"age":"1.1","code":23293,"gc":"Lo","kd":"play with; (Cant.) to provoke","kc":"liáo liǎo liào lǎo","kjo":"reu rau","kjk":"tawamureru mimeyoi tawareru midareru satoi","kk":"lyo","name":"CJK UNIFIED IDEOGRAPH-5AFD","type":"char"},{"age":"1.1","code":23294,"gc":"Lo","kc":"lián","name":"CJK UNIFIED IDEOGRAPH-5AFE","type":"char"},{"age":"1.1","code":23295,"gc":"Lo","kd":"tranquil","kc":"huà","kjo":"kaku gyaku","kjk":"shitoyaka mimeyoi","ky":[23155],"name":"CJK UNIFIED IDEOGRAPH-5AFF","type":"char"}]